alibabacloud_mcp_server/__init__.py
alibabacloud_mcp_server/api_meta_client.py
alibabacloud_mcp_server/cms_tools.py
alibabacloud_mcp_server/config.py
alibabacloud_mcp_server/oos_tools.py
alibabacloud_mcp_server/server.py
alibabacloud_mcp_server-0.7.1.dist-info/METADATA
alibabacloud_mcp_server-0.7.1.dist-info/WHEEL
alibabacloud_mcp_server-0.7.1.dist-info/entry_points.txt
alibabacloud_mcp_server-0.7.1.dist-info/licenses/LICENSE
alibabacloud_mcp_server-0.7.1.dist-info/RECORD
